{"IT": [{"id":0,"title":"  해외 여행객 증가…로밍의 진실 \"요금 폭탄 맞을까\"","url":"https://n.news.naver.com/mnews/article/277/0005118727?sid=105","image_url":"https://imgnews.pstatic.net/image/origin/277/2022/07/16/5118727.jpg?type=nf106_72","image_alt":"해외 여행객 증가…로밍의 진실 \"요금 폭탄 맞을까\"","summary":"2년 만에 하늘길이 열리면서 해외여행 수요가 늘고 있는 가운데 SK텔레콤이 관련 통신 상품을 16일 소개했다. 로밍 VS 현지유 …","date":"3시간전"},{"id":1,"title":"  [영상] “이걸 볼줄이야?” 비운의 ‘LG롤러블’ 깜짝 놀랄 실물 등장","url":"https://n.news.naver.com/mnews/article/016/0002016551?sid=105","image_url":"https://imgnews.pstatic.net/image/origin/016/2022/07/16/2016551.jpg?type=nf106_72","image_alt":"[영상] “이걸 볼줄이야?” 비운의 ‘LG롤러블’ 깜짝 놀랄 실물 등장","summary":"“LG 롤러블폰, 이렇게만 나왔어도…” 빛을 보지 못하고 사라진 LG전자 ‘롤러블 스마트폰’의 실제 구동 모습이 처음으로 공개됐 …","date":"3시간전"},{"id":2,"title":"  “1000만원→20만원, 실화냐” 난리치더니, 완전 헐값됐다","url":"https://n.news.naver.com/mnews/article/016/0002016546?sid=105","image_url":"https://imgnews.pstatic.net/image/origin/016/2022/07/16/2016546.jpg?type=nf106_72","image_alt":"“1000만원→20만원, 실화냐” 난리치더니, 완전 헐값됐다","summary":"“글로벌 유저 4000만명도 소용없네…입찰자 단 1명, ‘굴욕’ 당한 NFT.” 넷마블이 업계 최초로 시도한 ‘NFT(대체불가능 …","date":"4시간전"},{"id":3,"title":"  “비교해 봐, 중국이 그렇게 대단해?” 삼성 지독한 ‘홀대’","url":"https://n.news.naver.com/mnews/article/016/0002016544?sid=105","image_url":"https://imgnews.pstatic.net/image/origin/016/2022/07/16/2016544.jpg?type=nf106_72","image_alt":"“비교해 봐, 중국이 그렇게 대단해?” 삼성 지독한 ‘홀대’","summary":"“중국, 폴더블폰 마저 삼성 홀대 극심!” 중국이 삼성전자의 스마트폰 홀대가 점입가경이다. 삼성전자는 글로벌 폴더블(접는) 스마 …","date":"5시간전"},{"id":4,"title":"  한국대표단, 제63회 국제수학올림피아드에서 국가 종합 2위 차지","url":"https://n.news.naver.com/mnews/article/018/0005269559?sid=105","image_url":"https://imgnews.pstatic.net/image/origin/018/2022/07/16/5269559.jpg?type=nf106_72","image_alt":"한국대표단, 제63회 국제수학올림피아드에서 국가 종합 2위 차지","summary":"제63회 국제수학올림피아드에서 한국대표단이 국가 종합 2위를 기록했다. 지난 6일부터 16일까지 총 11일간 노르웨이 오슬로에서 …","date":"5시간전"},{"id":5,"title":"  “그렇게 잘 나가더니…” 하루 아침에 잘린 ‘이 여성’","url":"https://n.news.naver.com/mnews/article/016/0002016540?sid=105","image_url":"https://imgnews.pstatic.net/image/origin/016/2022/07/16/2016540.jpg?type=nf106_72","image_alt":"“그렇게 잘 나가더니…” 하루 아침에 잘린 ‘이 여성’","summary":"“‘이 여성’, 회사 ‘간판 모델’이었는데…하루 아침에 잘린 이유?” 전 세계적으로 가상인간(Virtual Human)을 회사의 …","date":"6시간전"},{"id":6,"title":"  비행 시뮬레이터 체험하는 관람객들","url":"https://n.news.naver.com/mnews/article/030/0003030857?sid=105","image_url":"https://imgnews.pstatic.net/image/origin/030/2022/07/16/3030857.jpg?type=nf106_72","image_alt":"비행 시뮬레이터 체험하는 관람객들","summary":"2022 대한민국 드론·UAM 박람회가 15~16일 서울 구로구 고척 스카이돔에서 열린 가운데 관람객들이 비행 시뮬레이터 체험을 …","date":"6시간전"},{"id":7,"title":"  2022 대한민국 드론·UAM 박람회","url":"https://n.news.naver.com/mnews/article/030/0003030855?sid=105","image_url":"https://imgnews.pstatic.net/image/origin/030/2022/07/16/3030855.jpg?type=nf106_72","image_alt":"2022 대한민국 드론·UAM 박람회","summary":"2022 대한민국 드론·UAM 박람회가 15~16일 서울 구로구 고척 스카이돔에서 열린 가운데 관람객들이 드론·UAM 전시물을  …","date":"6시간전"},{"id":8,"title":"  한국, 국제수학올림피아드 2위 쾌거…'전원 만점' 1위 어디","url":"https://n.news.naver.com/mnews/article/025/0003210074?sid=105","image_url":"https://imgnews.pstatic.net/image/origin/025/2022/07/16/3210074.jpg?type=nf106_72","image_alt":"한국, 국제수학올림피아드 2위 쾌거…'전원 만점' 1위 어디","summary":"올해 국제수학올림피아드에서 104개국 가운데 한국이 종합 2위를 차지했다. 16일 과학기술정보통신부에 따르면 지난 6일부터 16 …","date":"6시간전"},{"id":9,"title":"  한국, ‘국제수학올림피아드’ 2위 쾌거…1위는 놀랍게도 중국","url":"https://n.news.naver.com/mnews/article/016/0002016532?sid=105","image_url":"https://imgnews.pstatic.net/image/origin/016/2022/07/16/2016532.jpg?type=nf106_72","image_alt":"한국, ‘국제수학올림피아드’ 2위 쾌거…1위는 놀랍게도 중국","summary":"제63회 국제수학올림피아드(IMO)에 출전한 한국대표단 학생 6명 전원이 메달을 획득하는 쾌거를 달성했다. 이에 104개국 가운 …","date":"7시간전"}]}