[{"title":"\n\t\t\t\t\t\t\t\t \n\t\t\t\t\t\t\t\t\n\t\t\t\t\t\t\t\t 이스트시큐리티 \"랜섬웨어 차단 건수↓…여전히 높은 위험성\"\n\t\t\t\t\t\t\t\t","url":"https://n.news.naver.com/mnews/article/011/0004074196?sid=105","image_url":"https://imgnews.pstatic.net/image/origin/011/2022/07/08/4074196.jpg?type=nf106_72","image_alt":"이스트시큐리티 \"랜섬웨어 차단 건수↓…여전히 높은 위험성\"","summary":"올해 2분기 랜섬웨어 차단 건수가 직전 분기 대비 2만 9000건 이상 줄어든 것으로 나타났다. 8일 이스트시큐리티는 자사의 백 …","date":"1시간전\t"},{"title":"\n\t\t\t\t\t\t\t\t \n\t\t\t\t\t\t\t\t\n\t\t\t\t\t\t\t\t KISA, CJ올리브네트웍스·파인더갭과 버그바운티 대회 개최\n\t\t\t\t\t\t\t\t","url":"https://n.news.naver.com/mnews/article/014/0004864457?sid=105","image_url":"https://imgnews.pstatic.net/image/origin/014/2022/07/08/4864457.jpg?type=nf106_72","image_alt":"KISA, CJ올리브네트웍스·파인더갭과 버그바운티 대회 개최","summary":"한국인터넷진흥원(KISA)이 CJ올리브네트웍스·파인더갭과 함께 버그바운티 대회를 개최한다고 8일 밝혔다. 버그바운티란 기업의 서 …","date":"1시간전\t"},{"title":"\n\t\t\t\t\t\t\t\t \n\t\t\t\t\t\t\t\t\n\t\t\t\t\t\t\t\t [코인뉴스] 美 증시 훈풍에 비트코인 7% 이상↑...투심도 회복\n\t\t\t\t\t\t\t\t","url":"https://n.news.naver.com/mnews/article/119/0002619340?sid=105","image_url":"https://imgnews.pstatic.net/image/origin/119/2022/07/08/2619340.jpg?type=nf106_72","image_alt":"[코인뉴스] 美 증시 훈풍에 비트코인 7% 이상↑...투심도 회복","summary":"미국 증시 상승 영향으로 비트코인 가격도 오름세를 보이면서 투심도 조금씩 회복되는 모습이다. 8일 오후 2시 글로벌 코인시황 중 …","date":"2시간전\t"},{"title":"\n\t\t\t\t\t\t\t\t \n\t\t\t\t\t\t\t\t\n\t\t\t\t\t\t\t\t KISA·CJ올리브 '중소기업 보안 취약점' 찾는 대회 연다\n\t\t\t\t\t\t\t\t","url":"https://n.news.naver.com/mnews/article/421/0006205357?sid=105","image_url":"https://imgnews.pstatic.net/image/origin/421/2022/07/08/6205357.jpg?type=nf106_72","image_alt":"KISA·CJ올리브 '중소기업 보안 취약점' 찾는 대회 연다","summary":"한국인터넷진흥원(KISA)이 총 상금 3000만원을 걸고 중소기업의 소프트웨어(SW) 취약점을 찾는 대회를 연다. KISA는 C …","date":"6시간전\t"},{"title":"\n\t\t\t\t\t\t\t\t \n\t\t\t\t\t\t\t\t\n\t\t\t\t\t\t\t\t 무인매장 절도범죄 86% 증가…범인 10명 중 3명 '10대'\n\t\t\t\t\t\t\t\t","url":"https://n.news.naver.com/mnews/article/421/0006204398?sid=105","image_url":"https://imgnews.pstatic.net/image/origin/421/2022/07/07/6204398.jpg?type=nf106_72","image_alt":"무인매장 절도범죄 86% 증가…범인 10명 중 3명 '10대'","summary":"지난해 무인매장 절도 범죄가 전년보다 85.7% 증가한 것으로 나타났다. 삼성그룹 보안기업 에스원은 지난 2020년 1월부터 올 …","date":"22시간전\t"},{"title":"\n\t\t\t\t\t\t\t\t \n\t\t\t\t\t\t\t\t\n\t\t\t\t\t\t\t\t KT클라우드 '서버 10만대 수용'…초거대 데이터센터 가산에 세운다\n\t\t\t\t\t\t\t\t","url":"https://n.news.naver.com/mnews/article/011/0004073852?sid=105","image_url":"https://imgnews.pstatic.net/image/origin/011/2022/07/07/4073852.jpg?type=nf106_72","image_alt":"KT클라우드 '서버 10만대 수용'…초거대 데이터센터 가산에 세운다","summary":"빠르게 성장하는 기업 디지털 전환(DX)에 발맞춰 KT(030200)클라우드가 서울에 초거대(하이퍼스케일) 인터넷데이터센터(ID …","date":"23시간전\t"},{"title":"\n\t\t\t\t\t\t\t\t \n\t\t\t\t\t\t\t\t\n\t\t\t\t\t\t\t\t [코인뉴스] 비트코인은 동면중... 탈(脫)거래소 현상 심화\n\t\t\t\t\t\t\t\t","url":"https://n.news.naver.com/mnews/article/119/0002619070?sid=105","image_url":"https://imgnews.pstatic.net/image/origin/119/2022/07/07/2619070.jpg?type=nf106_72","image_alt":"[코인뉴스] 비트코인은 동면중... 탈(脫)거래소 현상 심화","summary":"대장 암호화폐인 비트코인 상당수가 거래소에서 개인 오프라인 지갑으로 빠져나와 '동면'하고 있다는 분석이 나왔다. 7일(현지시간) …","date":"23시간전\t"},{"title":"\n\t\t\t\t\t\t\t\t \n\t\t\t\t\t\t\t\t\n\t\t\t\t\t\t\t\t 역대급 개인정보 유출 사고?…\"中 10억명 데이터 훔쳤다\" [데이터링]\n\t\t\t\t\t\t\t\t","url":"https://n.news.naver.com/mnews/article/031/0000683830?sid=105","image_url":"https://imgnews.pstatic.net/image/origin/031/2022/07/07/683830.jpg?type=nf106_72","image_alt":"역대급 개인정보 유출 사고?…\"中 10억명 데이터 훔쳤다\" [데이터링]","summary":"개인정보가 사이버 범죄자의 새로운 먹잇감으로 부상한 가운데 최근 한 해커가 중국인 10억 명의 개인정보를 빼돌렸다고 주장하면서  …","date":"1일전"},{"title":"\n\t\t\t\t\t\t\t\t \n\t\t\t\t\t\t\t\t\n\t\t\t\t\t\t\t\t “10대들, 주말 오전 무인매장 현금 노린다”··· 에스원, 범죄 동향 분석 발표\n\t\t\t\t\t\t\t\t","url":"https://n.news.naver.com/mnews/article/138/0002128142?sid=105","image_url":"https://imgnews.pstatic.net/image/origin/138/2022/07/07/2128142.jpg?type=nf106_72","image_alt":"“10대들, 주말 오전 무인매장 현금 노린다”··· 에스원, 범죄 동향 분석 발표","summary":"코로나19 대유행 이후 무인매장의 수가 늘어나는 가운데 10대들이 주말 오전 시간대에 무인매장 내 현금을 노리는 경우가 많은 것 …","date":"1일전"},{"title":"\n\t\t\t\t\t\t\t\t \n\t\t\t\t\t\t\t\t\n\t\t\t\t\t\t\t\t KISA-CJ올리브네트웍스, 총 상금 3천만원 규모의 버그바운티 대회 연다\n\t\t\t\t\t\t\t\t","url":"https://n.news.naver.com/mnews/article/138/0002128141?sid=105","image_url":"https://imgnews.pstatic.net/image/origin/138/2022/07/07/2128141.jpg?type=nf106_72","image_alt":"KISA-CJ올리브네트웍스, 총 상금 3천만원 규모의 버그바운티 대회 연다","summary":"CJ올리브네트웍스(대표이사 차인혁)와 한국인터넷진흥원(원장 이원태, 이하 KISA)은 파인더갭과 함께 총 상금 3000만원 규모 …","date":"1일전"}]